HAPPE/INDELANN.py
HAPPE/SNPANN_upgrade_3.py
HAPPE/__init__.py
HAPPE/depth2excel.py
HAPPE/excel_haplotype.py
HAPPE/filter_codingregion_SNP.py
HAPPE/filter_functional_SNP.py
HAPPE/filter_noncodingregion_SNP.py
HAPPE/hierarchy_clustering.py
HAPPE/normalization_depth_from_mosdepth_output.py
HAPPE/pheat2excel_V5.py
HAPPE/prepare_additive_effect.py
HAPPE/sampleinf2excel_V2.py
HAPPE/tree2excel_v3.py
HAPPE/vcf2heatmatrix.py
HAPPE-0.1.5.dist-info/LICENSE
HAPPE-0.1.5.dist-info/METADATA
HAPPE-0.1.5.dist-info/WHEEL
HAPPE-0.1.5.dist-info/entry_points.txt
HAPPE-0.1.5.dist-info/top_level.txt
HAPPE-0.1.5.dist-info/RECORD
