Metadata-Version: 2.1
Name: HAPPE
Version: 0.1.5
Summary: A tool to visualize the haplotype pattern and various information in excel.
Home-page: UNKNOWN
Author: Cong Feng
Author-email: congfeng97@gmail.com
License: UNKNOWN
Platform: UNKNOWN
Classifier: Programming Language :: Python :: 3
Classifier: License :: OSI Approved :: MIT License
Classifier: Operating System :: OS Independent
Requires-Python: >=3.6
License-File: LICENSE
Requires-Dist: argparse
Requires-Dist: pandas
Requires-Dist: numpy
Requires-Dist: scipy
Requires-Dist: sklearn
Requires-Dist: openpyxl
Requires-Dist: ConfigParser
Requires-Dist: dynamicTreeCut
